blindfoldpy/__init__.py
blindfoldpy/main.py
blindfoldpy-0.1.1.dist-info/LICENSE
blindfoldpy-0.1.1.dist-info/METADATA
blindfoldpy-0.1.1.dist-info/WHEEL
blindfoldpy-0.1.1.dist-info/entry_points.txt
blindfoldpy-0.1.1.dist-info/top_level.txt
blindfoldpy-0.1.1.dist-info/RECORD
