Metadata-Version: 2.1
Name: blindfoldpy
Version: 0.1.1
Summary: Don't use this. Use the real blindfold. I'm just trying to spite the author who's a close friend of mine.
Home-page: https://github.com/iwishiwasaneagle/blindfold.py
Author: iwishiwasaneagle
Author-email: jh.ewers@gmail.com
License: UNKNOWN
Platform: UNKNOWN
Classifier: Programming Language :: Python :: 3
Classifier: License :: OSI Approved :: GNU General Public License v3 (GPLv3)
Classifier: Operating System :: OS Independent
Requires-Python: >=3.6
License-File: LICENSE
Requires-Dist: requests (==2.26.0)
